{
    "id": "shift around",
    "variation": "resolved",
    "scrollSpeed": 4,
    "bpmChanges": [
        {
            "t": 0,
            "bpm": 100
        }
    ],
    "events": [
        {
            "time": 12600,
            "id": "beatmonsters-stop"
        },
        {
            "time": 19200,
            "id": "beatmonsters-resume"
        },
        {
            "time": 28049,
            "id": "beatmonsters-stop"
        },
        {
            "time": 31200,
            "id": "beatmonsters-resume"
        },
        {
            "time": 40379,
            "id": "beatmonsters-stop"
        }
    ]
}